accounts/__init__.py
accounts/admin.py
accounts/apps.py
accounts/models.py
accounts/tests.py
accounts/urls.py
accounts/views.py
accounts/migrations/0001_initial.py
accounts/migrations/__init__.py
core/__init__.py
core/asgi.py
core/settings.py
core/urls.py
core/wsgi.py
home/__init__.py
home/admin.py
home/apps.py
home/forms.py
home/models.py
home/tests.py
home/urls.py
home/views.py
home/migrations/0001_initial.py
home/migrations/0002_delete_attendance_delete_attendance_list_and_more.py
home/migrations/0003_initial.py
home/migrations/0004_attendance_list.py
home/migrations/0005_delete_attendance_list.py
home/migrations/0006_attendance_list.py
home/migrations/0007_delete_attendance_list.py
home/migrations/0008_attendance_list.py
home/migrations/0009_remove_attendance_list_ip.py
home/migrations/0010_attendance_list_ip_attendance_list_login_id.py
home/migrations/0011_attendance_list_status.py
home/migrations/0012_rename_login_id_attendance_list_loginid_and_more.py
home/migrations/0013_dr.py
home/migrations/0014_remove_attendance_list_qrcode_and_more.py
home/migrations/0015_attendance.py
home/migrations/0016_attendance_list.py
home/migrations/0017_rename_name_attendance_subject_name.py
home/migrations/0018_leave_list_leave.py
home/migrations/0019_alter_leave_list_qrcode.py
home/migrations/0020_alter_leave_qr_code.py
home/migrations/__init__.py
attendance_and_leaving_system_using_qr_code_main-0.1.0.dist-info/METADATA
attendance_and_leaving_system_using_qr_code_main-0.1.0.dist-info/WHEEL
attendance_and_leaving_system_using_qr_code_main-0.1.0.dist-info/top_level.txt
attendance_and_leaving_system_using_qr_code_main-0.1.0.dist-info/RECORD
