Metadata-Version: 2.4
Name: Attendance-and-leaving-system-using-QR-Code-main
Version: 0.1.0
Requires-Dist: Django>=4.0
Dynamic: requires-dist
